examples/__init__.py
examples/arcade_bot.py
examples/bot_vs_bot.py
examples/distributed_workers.py
examples/fastreload.py
examples/host_external_norestart.py
examples/observer_easy_vs_easy.py
examples/play_tvz.py
examples/run_external.py
examples/show_debug.py
examples/too_slow_bot.py
examples/worker_rush.py
examples/protoss/__init__.py
examples/protoss/cannon_rush.py
examples/protoss/threebase_voidray.py
examples/protoss/warpgate_push.py
examples/terran/__init__.py
examples/terran/cyclone_push.py
examples/terran/mass_reaper.py
examples/terran/onebase_battlecruiser.py
examples/terran/proxy_rax.py
examples/terran/ramp_wall.py
examples/zerg/__init__.py
examples/zerg/hydralisk_push.py
examples/zerg/onebase_broodlord.py
examples/zerg/zerg_rush.py
sc2/__init__.py
sc2/action.py
sc2/bot_ai.py
sc2/cache.py
sc2/client.py
sc2/constants.py
sc2/controller.py
sc2/data.py
sc2/game_data.py
sc2/game_info.py
sc2/game_state.py
sc2/main.py
sc2/maps.py
sc2/paths.py
sc2/pixel_map.py
sc2/player.py
sc2/portconfig.py
sc2/position.py
sc2/power_source.py
sc2/protocol.py
sc2/renderer.py
sc2/sc2process.py
sc2/score.py
sc2/tmpfix.py
sc2/unit.py
sc2/unit_command.py
sc2/units.py
sc2/helpers/__init__.py
sc2/helpers/control_group.py
sc2/helpers/devtools.py
sc2/ids/__init__.py
sc2/ids/ability_id.py
sc2/ids/buff_id.py
sc2/ids/effect_id.py
sc2/ids/unit_typeid.py
sc2/ids/upgrade_id.py
sc2-0.11.2.dist-info/LICENSE
sc2-0.11.2.dist-info/METADATA
sc2-0.11.2.dist-info/WHEEL
sc2-0.11.2.dist-info/top_level.txt
sc2-0.11.2.dist-info/RECORD
