Metadata-Version: 1.1
Name: sc2
Version: 0.11.2
Summary: A StarCraft II API Client for Python 3
Home-page: https://github.com/Dentosal/python-sc2
Author: Hannes Karppila
Author-email: hannes.karppila@gmail.com
License: MIT
Keywords: StarCraft,StarCraft 2,StarCraft II,AI,Bot
Platform: UNKNOWN
Classifier: Development Status :: 3 - Alpha
Classifier: Intended Audience :: Developers
Classifier: Intended Audience :: Education
Classifier: Intended Audience :: Science/Research
Classifier: Topic :: Games/Entertainment
Classifier: Topic :: Games/Entertainment :: Real Time Strategy
Classifier: Topic :: Scientific/Engineering
Classifier: Topic :: Scientific/Engineering :: Artificial Intelligence
Classifier: License :: OSI Approved :: MIT License
Classifier: Programming Language :: Python :: 3
Classifier: Programming Language :: Python :: 3.6
Classifier: Programming Language :: Python :: 3.7
